{
  "folder": "UOqvWas8iwkznSYJ",
  "name": "Brawler",
  "type": "talent",
  "_id": "wqv4X5X3UnM9TVfy",
  "img": "icons/svg/item-bag.svg",
  "system": {
    "formula": "",
    "description": "<p>You gain a point of favor on tests made to grapple creatures.</p>",
    "parent": "",
    "tree": "Warfare-1",
    "position": 2,
    "attributes": {
      "cost": []
    },
    "points": {
      "body": 3,
      "mind": 0,
      "soul": 1
    },
    "ultimate": true
  },
  "effects": [],
  "sort": 200000,
  "ownership": {
    "default": 0,
    "nLkleFyXeCclB3Jg": 3
  },
  "flags": {},
  "_stats": {
    "compendiumSource": null,
    "duplicateSource": null,
    "coreVersion": "12.331",
    "systemId": "utopia",
    "systemVersion": "0.1.0",
    "createdTime": 1731481573410,
    "modifiedTime": 1731518590752,
    "lastModifiedBy": "nLkleFyXeCclB3Jg"
  },
  "_key": "!items!wqv4X5X3UnM9TVfy"
}
