{
  "name": "Thick Skin",
  "type": "talent",
  "_id": "sW8t5AppSIUI5nM1",
  "img": "icons/svg/item-bag.svg",
  "system": {
    "formula": "",
    "description": "<p>Your Physical defense increases by 4.</p>",
    "parent": "Compendium.utopia.species.Item.BoWN6px3m4QIZFjI",
    "tree": "Demonic Cambion",
    "position": 1,
    "attributes": {
      "cost": []
    },
    "points": {
      "body": 1,
      "mind": 1,
      "soul": 0
    },
    "parentItem": {
      "name": "Demonic Cambion",
      "type": "species",
      "_id": "BoWN6px3m4QIZFjI",
      "img": "icons/svg/item-bag.svg",
      "system": {
        "description": "",
        "name": "Human",
        "grants": {
          "block": "2d4",
          "dodge": "2d12",
          "constitution": 4,
          "endurance": "6",
          "effervescence": "2",
          "subtraits": 2,
          "languages": "utopian,primordial"
        }
      },
      "effects": [],
      "folder": null,
      "sort": 0,
      "ownership": {
        "default": 0,
        "nLkleFyXeCclB3Jg": 3
      },
      "flags": {},
      "_stats": {
        "compendiumSource": null,
        "duplicateSource": null,
        "coreVersion": "12.331",
        "systemId": "utopia",
        "systemVersion": "0.1.0",
        "createdTime": 1731344008598,
        "modifiedTime": 1731344021043,
        "lastModifiedBy": "nLkleFyXeCclB3Jg"
      }
    },
    "roll": "",
    "ultimate": true
  },
  "effects": [
    {
      "name": "Thick Skin",
      "origin": "Compendium.utopia.talents.Item.sW8t5AppSIUI5nM1",
      "duration": {
        "rounds": null,
        "startTime": null,
        "seconds": null,
        "combat": null,
        "turns": null,
        "startRound": null,
        "startTurn": null
      },
      "disabled": false,
      "img": "icons/svg/aura.svg",
      "_id": "ULTn2MsSi54GMi7i",
      "type": "base",
      "system": {},
      "changes": [
        {
          "key": "system.defenses.physical",
          "mode": 2,
          "value": "4",
          "priority": null
        }
      ],
      "description": "",
      "tint": "#ffffff",
      "transfer": true,
      "statuses": [],
      "sort": 0,
      "flags": {},
      "_stats": {
        "compendiumSource": null,
        "duplicateSource": null,
        "coreVersion": "12.331",
        "systemId": "utopia",
        "systemVersion": "0.1.0",
        "createdTime": 1731392282899,
        "modifiedTime": 1731392302772,
        "lastModifiedBy": "nLkleFyXeCclB3Jg"
      },
      "_key": "!items.effects!sW8t5AppSIUI5nM1.ULTn2MsSi54GMi7i"
    }
  ],
  "folder": "EzNELKOkcTjd7pOU",
  "sort": 100782,
  "ownership": {
    "default": 0,
    "nLkleFyXeCclB3Jg": 3
  },
  "flags": {},
  "_stats": {
    "compendiumSource": null,
    "duplicateSource": null,
    "coreVersion": "12.331",
    "systemId": "utopia",
    "systemVersion": "0.1.0",
    "createdTime": 1731392260024,
    "modifiedTime": 1731480919594,
    "lastModifiedBy": "nLkleFyXeCclB3Jg"
  },
  "_key": "!items!sW8t5AppSIUI5nM1"
}
